Maxar_OGC/__init__.py
Maxar_OGC/auth.py
Maxar_OGC/cli_commands.py
Maxar_OGC/interface.py
Maxar_OGC/process.py
Maxar_OGC/wcs.py
Maxar_OGC/wfs.py
Maxar_OGC/wms.py
Maxar_OGC/wmts.py
Maxar_OGC-1.5.0.dist-info/LICENSE
Maxar_OGC-1.5.0.dist-info/LICENSE.txt
Maxar_OGC-1.5.0.dist-info/METADATA
Maxar_OGC-1.5.0.dist-info/WHEEL
Maxar_OGC-1.5.0.dist-info/entry_points.txt
Maxar_OGC-1.5.0.dist-info/top_level.txt
Maxar_OGC-1.5.0.dist-info/RECORD
