Metadata-Version: 2.1
Name: Maxar-OGC
Version: 1.5.0
Summary: SDK for interacting with Maxar imagery platforms
Author: GCS Marianas Team
Author-email: DL-GCS-Marianas@digitalglobe.com
License: MIT
Project-URL: Documentation, https://cloudservices.readthedocs.io/en/latest/index.html
Project-URL: Source, https://github.com/DigitalGlobe/CloudServices
Keywords: OGC,WMS,WFS,WMTS,WCS,MAXAR,IMAGERY,GIS
Classifier: Development Status :: 5 - Production/Stable
Classifier: Intended Audience :: Developers
Classifier: Topic :: Software Development :: Build Tools
Classifier: License :: OSI Approved :: MIT License
Classifier: Programming Language :: Python :: 3.7
Classifier: Programming Language :: Python :: 3.8
Classifier: Programming Language :: Python :: 3.9
Requires-Python: >=3.8
License-File: LICENSE
License-File: LICENSE.txt
Requires-Dist: pyproj
Requires-Dist: shapely
Requires-Dist: requests
Requires-Dist: ipython
Requires-Dist: pillow
Requires-Dist: click
Requires-Dist: beautifulsoup4
Requires-Dist: lxml
